pygenstability/__init__.py
pygenstability/app.py
pygenstability/constructors.py
pygenstability/data_clustering.py
pygenstability/generalized_louvain.cpython-314-x86_64-linux-musl.so
pygenstability/io.py
pygenstability/optimal_scales.py
pygenstability/plotting.py
pygenstability/pygenstability.py
pygenstability/contrib/__init__.py
pygenstability/contrib/sankey.py
pygenstability/generalized_louvain/generalized_louvain.cpp
pygenstability.libs/libgcc_s-0cd532bd.so.1
pygenstability.libs/libstdc++-5d72f927.so.6.0.33
pygenstability-0.2.5.dist-info/METADATA
pygenstability-0.2.5.dist-info/WHEEL
pygenstability-0.2.5.dist-info/entry_points.txt
pygenstability-0.2.5.dist-info/top_level.txt
pygenstability-0.2.5.dist-info/RECORD
pygenstability-0.2.5.dist-info/licenses/LICENSE
