Metadata-Version: 2.1
Name: PyGenStability
Version: 0.2.5
Summary: Python binding of generalised Louvain with Markov Stability
Home-page: https://github.com/ImperialCollegeLondon/PyGenStability
Author: Alexis Arnaudon, Dominik Schindler
Author-email: alexis.arnaudon@epfl.ch, dominik.schindler19@imperial.ac.uk
License-File: LICENSE
Requires-Dist: numpy>=1.18.1
Requires-Dist: scipy>=1.4.1
Requires-Dist: matplotlib>=3.1.3
Requires-Dist: scikit-learn
Requires-Dist: cmake>=3.16.3
Requires-Dist: click>=7.0
Requires-Dist: tqdm>=4.45.0
Requires-Dist: pybind11>=2.10.0
Requires-Dist: pandas>=1.0.0
Requires-Dist: threadpoolctl
Provides-Extra: all
Requires-Dist: plotly>=3.6.0; extra == "all"
Requires-Dist: pyyaml; extra == "all"
Requires-Dist: dictdiffer; extra == "all"
Requires-Dist: pytest; extra == "all"
Requires-Dist: pytest-cov; extra == "all"
Requires-Dist: pytest-html; extra == "all"
Requires-Dist: diff-pdf-visually; extra == "all"
Requires-Dist: ipython!=8.7.0; extra == "all"
Requires-Dist: igraph; extra == "all"
Requires-Dist: leidenalg; extra == "all"
Requires-Dist: networkx>=3.0; extra == "all"
Provides-Extra: leiden
Requires-Dist: igraph; extra == "leiden"
Requires-Dist: leidenalg; extra == "leiden"
Provides-Extra: networkx
Requires-Dist: networkx>=3.0; extra == "networkx"
Provides-Extra: plotly
Requires-Dist: plotly>=3.6.0; extra == "plotly"
